{"nodes": [{"id": "d_duancanhan_project_quanlygiaidau_app_quanly_giaidau_lib_domain_entities_team_dart", "label": "team.dart", "file_type": "code", "source_file": "lib/domain/entities/team.dart", "source_location": null}, {"id": "entities_team_team", "label": "Team", "file_type": "code", "source_file": "lib/domain/entities/team.dart", "source_location": null}, {"id": "entities_team_id", "label": "id", "file_type": "code", "source_file": "lib/domain/entities/team.dart", "source_location": null}, {"id": "entities_team_name", "label": "name", "file_type": "code", "source_file": "lib/domain/entities/team.dart", "source_location": null}, {"id": "entities_team_members", "label": "members", "file_type": "code", "source_file": "lib/domain/entities/team.dart", "source_location": null}, {"id": "list", "label": "List", "file_type": "code", "source_file": null, "source_location": null}, {"id": "entities_team_seed", "label": "seed", "file_type": "code", "source_file": "lib/domain/entities/team.dart", "source_location": null}, {"id": "entities_team_group", "label": "group", "file_type": "code", "source_file": "lib/domain/entities/team.dart", "source_location": null}, {"id": "entities_team_photourl", "label": "photoUrl", "file_type": "code", "source_file": "lib/domain/entities/team.dart", "source_location": null}, {"id": "entities_team_qrcode", "label": "qrCode", "file_type": "code", "source_file": "lib/domain/entities/team.dart", "source_location": null}, {"id": "entities_team_ischeckedin", "label": "isCheckedIn", "file_type": "code", "source_file": "lib/domain/entities/team.dart", "source_location": null}, {"id": "entities_team_contactemail", "label": "contactEmail", "file_type": "code", "source_file": "lib/domain/entities/team.dart", "source_location": null}, {"id": "entities_team_createdat", "label": "createdAt", "file_type": "code", "source_file": "lib/domain/entities/team.dart", "source_location": null}, {"id": "datetime", "label": "DateTime", "file_type": "code", "source_file": null, "source_location": null}, {"id": "entities_team_fromjson", "label": "fromJson", "file_type": "code", "source_file": "lib/domain/entities/team.dart", "source_location": null}, {"id": "entities_team_tojson", "label": "toJson", "file_type": "code", "source_file": "lib/domain/entities/team.dart", "source_location": null}, {"id": "entities_team_copywith", "label": "copyWith", "file_type": "code", "source_file": "lib/domain/entities/team.dart", "source_location": null}, {"id": "entities_team_tostring", "label": "toString", "file_type": "code", "source_file": "lib/domain/entities/team.dart", "source_location": null}, {"id": "package_app_quanly_giaidau_core_utils_date_parser_dart", "label": "package:app_quanly_giaidau/core/utils/date_parser.dart", "file_type": "code", "source_file": null, "source_location": null}], "edges": [{"source": "d_duancanhan_project_quanlygiaidau_app_quanly_giaidau_lib_domain_entities_team_dart", "target": "entities_team_team", "relation": "defines", "confidence": "EXTRACTED", "confidence_score": 1.0, "source_file": "lib/domain/entities/team.dart", "source_location": null, "weight": 1.0}, {"source": "d_duancanhan_project_quanlygiaidau_app_quanly_giaidau_lib_domain_entities_team_dart", "target": "entities_team_id", "relation": "defines", "confidence": "EXTRACTED", "confidence_score": 1.0, "source_file": "lib/domain/entities/team.dart", "source_location": null, "weight": 1.0}, {"source": "d_duancanhan_project_quanlygiaidau_app_quanly_giaidau_lib_domain_entities_team_dart", "target": "entities_team_name", "relation": "defines", "confidence": "EXTRACTED", "confidence_score": 1.0, "source_file": "lib/domain/entities/team.dart", "source_location": null, "weight": 1.0}, {"source": "d_duancanhan_project_quanlygiaidau_app_quanly_giaidau_lib_domain_entities_team_dart", "target": "entities_team_members", "relation": "defines", "confidence": "EXTRACTED", "confidence_score": 1.0, "source_file": "lib/domain/entities/team.dart", "source_location": null, "weight": 1.0}, {"source": "d_duancanhan_project_quanlygiaidau_app_quanly_giaidau_lib_domain_entities_team_dart", "target": "list", "relation": "references", "confidence": "EXTRACTED", "confidence_score": 1.0, "source_file": "lib/domain/entities/team.dart", "source_location": null, "weight": 1.0, "context": "variable_type"}, {"source": "d_duancanhan_project_quanlygiaidau_app_quanly_giaidau_lib_domain_entities_team_dart", "target": "entities_team_seed", "relation": "defines", "confidence": "EXTRACTED", "confidence_score": 1.0, "source_file": "lib/domain/entities/team.dart", "source_location": null, "weight": 1.0}, {"source": "d_duancanhan_project_quanlygiaidau_app_quanly_giaidau_lib_domain_entities_team_dart", "target": "entities_team_group", "relation": "defines", "confidence": "EXTRACTED", "confidence_score": 1.0, "source_file": "lib/domain/entities/team.dart", "source_location": null, "weight": 1.0}, {"source": "d_duancanhan_project_quanlygiaidau_app_quanly_giaidau_lib_domain_entities_team_dart", "target": "entities_team_photourl", "relation": "defines", "confidence": "EXTRACTED", "confidence_score": 1.0, "source_file": "lib/domain/entities/team.dart", "source_location": null, "weight": 1.0}, {"source": "d_duancanhan_project_quanlygiaidau_app_quanly_giaidau_lib_domain_entities_team_dart", "target": "entities_team_qrcode", "relation": "defines", "confidence": "EXTRACTED", "confidence_score": 1.0, "source_file": "lib/domain/entities/team.dart", "source_location": null, "weight": 1.0}, {"source": "d_duancanhan_project_quanlygiaidau_app_quanly_giaidau_lib_domain_entities_team_dart", "target": "entities_team_ischeckedin", "relation": "defines", "confidence": "EXTRACTED", "confidence_score": 1.0, "source_file": "lib/domain/entities/team.dart", "source_location": null, "weight": 1.0}, {"source": "d_duancanhan_project_quanlygiaidau_app_quanly_giaidau_lib_domain_entities_team_dart", "target": "entities_team_contactemail", "relation": "defines", "confidence": "EXTRACTED", "confidence_score": 1.0, "source_file": "lib/domain/entities/team.dart", "source_location": null, "weight": 1.0}, {"source": "d_duancanhan_project_quanlygiaidau_app_quanly_giaidau_lib_domain_entities_team_dart", "target": "entities_team_createdat", "relation": "defines", "confidence": "EXTRACTED", "confidence_score": 1.0, "source_file": "lib/domain/entities/team.dart", "source_location": null, "weight": 1.0}, {"source": "d_duancanhan_project_quanlygiaidau_app_quanly_giaidau_lib_domain_entities_team_dart", "target": "datetime", "relation": "references", "confidence": "EXTRACTED", "confidence_score": 1.0, "source_file": "lib/domain/entities/team.dart", "source_location": null, "weight": 1.0, "context": "variable_type"}, {"source": "d_duancanhan_project_quanlygiaidau_app_quanly_giaidau_lib_domain_entities_team_dart", "target": "entities_team_fromjson", "relation": "defines", "confidence": "EXTRACTED", "confidence_score": 1.0, "source_file": "lib/domain/entities/team.dart", "source_location": null, "weight": 1.0}, {"source": "d_duancanhan_project_quanlygiaidau_app_quanly_giaidau_lib_domain_entities_team_dart", "target": "entities_team_tojson", "relation": "defines", "confidence": "EXTRACTED", "confidence_score": 1.0, "source_file": "lib/domain/entities/team.dart", "source_location": null, "weight": 1.0}, {"source": "d_duancanhan_project_quanlygiaidau_app_quanly_giaidau_lib_domain_entities_team_dart", "target": "entities_team_copywith", "relation": "defines", "confidence": "EXTRACTED", "confidence_score": 1.0, "source_file": "lib/domain/entities/team.dart", "source_location": null, "weight": 1.0}, {"source": "d_duancanhan_project_quanlygiaidau_app_quanly_giaidau_lib_domain_entities_team_dart", "target": "entities_team_tostring", "relation": "defines", "confidence": "EXTRACTED", "confidence_score": 1.0, "source_file": "lib/domain/entities/team.dart", "source_location": null, "weight": 1.0}, {"source": "d_duancanhan_project_quanlygiaidau_app_quanly_giaidau_lib_domain_entities_team_dart", "target": "package_app_quanly_giaidau_core_utils_date_parser_dart", "relation": "imports", "confidence": "EXTRACTED", "confidence_score": 1.0, "source_file": "lib/domain/entities/team.dart", "source_location": null, "weight": 1.0}]}